bluerpc_service/__init__.py
bluerpc_service/ble.py
bluerpc_service/cli.py
bluerpc_service/worker.py
bluerpc_service/rpc/__init__.py
bluerpc_service/rpc/ble_pb2.py
bluerpc_service/rpc/ble_pb2_grpc.py
bluerpc_service/rpc/btc_pb2.py
bluerpc_service/rpc/btc_pb2_grpc.py
bluerpc_service/rpc/common_pb2.py
bluerpc_service/rpc/common_pb2_grpc.py
bluerpc_service/rpc/worker_pb2.py
bluerpc_service/rpc/worker_pb2_grpc.py
bluerpc_service-0.0.8.dist-info/METADATA
bluerpc_service-0.0.8.dist-info/WHEEL
bluerpc_service-0.0.8.dist-info/entry_points.txt
bluerpc_service-0.0.8.dist-info/top_level.txt
bluerpc_service-0.0.8.dist-info/RECORD
