Metadata-Version: 2.1
Name: bluerpc-service
Version: 0.0.8
Summary: Bluetooth Service for BlueRPC
Home-page: https://github.com/BlueRPC/service
Author: drosocode
License: MIT
Project-URL: Documentation, https://bluerpc.github.io/components/workers/service/
Project-URL: Source, https://github.com/BlueRPC/service
Classifier: Programming Language :: Python :: 3
Classifier: License :: OSI Approved :: MIT License
Classifier: Operating System :: OS Independent
Requires-Python: >=3.7
Requires-Dist: bleak
Requires-Dist: grpcio
Requires-Dist: protobuf
